jupyter_server_proxy/__init__.py
jupyter_server_proxy/api.py
jupyter_server_proxy/config.py
jupyter_server_proxy/handlers.py
jupyter_server_proxy/utils.py
jupyter_server_proxy/websocket.py
jupyter_server_proxy/etc/jupyter-server-proxy-nbextension.json
jupyter_server_proxy/etc/jupyter-server-proxy-serverextension.json
jupyter_server_proxy/static/tree.js
jupyter_server_proxy_noe-1.1.data/data/etc/jupyter/jupyter_notebook_config.d/jupyter-server-proxy-serverextension.json
jupyter_server_proxy_noe-1.1.data/data/etc/jupyter/nbconfig/tree.d/jupyter-server-proxy-nbextension.json
jupyter_server_proxy_noe-1.1.data/data/share/jupyter/nbextensions/jupyter_server_proxy/tree.js
jupyter_server_proxy_noe-1.1.dist-info/LICENSE
jupyter_server_proxy_noe-1.1.dist-info/METADATA
jupyter_server_proxy_noe-1.1.dist-info/WHEEL
jupyter_server_proxy_noe-1.1.dist-info/top_level.txt
jupyter_server_proxy_noe-1.1.dist-info/RECORD
