Metadata-Version: 2.1
Name: jupyter-server-proxy-noe
Version: 1.1
Summary: Jupyter server extension to supervise and proxy web services
Home-page: https://github.com/NoeB/jupyter-server-proxy
Author: Ryan Lovett & Yuvi Panda
Author-email: rylo@berkeley.edu
License: BSD 3-Clause
Platform: UNKNOWN
Classifier: Framework :: Jupyter
Requires-Python: >=3.5
Requires-Dist: notebook
Requires-Dist: simpervisor (>=0.2)
Requires-Dist: aiohttp
